./.gitignore
./PKG-INFO
./README.md
./__init__.py
./image_vec_rep.py
./pyproject.toml
./test.py
feluda_image_vec_rep_resnet-0.1.6.dist-info/METADATA
feluda_image_vec_rep_resnet-0.1.6.dist-info/WHEEL
feluda_image_vec_rep_resnet-0.1.6.dist-info/RECORD
