Metadata-Version: 2.4
Name: feluda-image-vec-rep-resnet
Version: 0.1.6
Requires-Python: >=3.10
Requires-Dist: feluda[image]
Requires-Dist: numpy<2.2.0,>=1.26
Requires-Dist: pillow>=11.1.0
Requires-Dist: torch>=2.6.0
Requires-Dist: torchvision>=0.21.0
